{"type_of": "user", "id": 16205, "username": "nicksaraev", "name": "Nick", "twitter_username": null, "github_username": "njsaraev", "email": null, "summary": "Nick Saraev is a writer & entrepreneur who pivoted from a path in medicine to forge a series of successful digital media businesses. He's been featured in Popular Mechanics, Apple News, & Bloomberg.", "location": "United States", "website_url": "https://nicksaraev.com/", "joined_at": "Dec 22, 2023", "profile_image": "https://community.codenewbie.org/images/D1sgX9QCkX69zrY7bK31BuRqbmLDHHdCEQaA5fSSIN0/rs:fill:320:320/g:sm/mb:500000/ar:1/aHR0cHM6Ly9jb21t/dW5pdHkuY29kZW5l/d2JpZS5vcmcvcmVt/b3RlaW1hZ2VzL3Vw/bG9hZHMvdXNlci9w/cm9maWxlX2ltYWdl/LzE2MjA1LzNjMzA5/MTgxLTc1ZWQtNGNk/MS1hMTcyLThiN2M1/ZjY0YWZjOS5wbmc", "badge_ids": [], "article_count": 1}