{"type_of": "user", "id": 16948, "username": "exastrisapk", "name": "Ex Astris APK", "twitter_username": null, "github_username": "ExAstrisAPK", "email": null, "summary": "Explore galaxies, fight aliens, and build your spaceship in Ex Astris, a captivating mobile RPG. Download the free latest version (v1.0.4) and embark on an interstellar adventure today.", "location": "", "website_url": "https://exastrisapk.com/", "joined_at": "Mar  3, 2024", "profile_image": "https://community.codenewbie.org/images/QkBYMT4u6gmndaDRULATtSsod_HnEgSMBufVNg-xack/rs:fill:320:320/g:sm/mb:500000/ar:1/aHR0cHM6Ly9jb21t/dW5pdHkuY29kZW5l/d2JpZS5vcmcvcmVt/b3RlaW1hZ2VzL3Vw/bG9hZHMvdXNlci9w/cm9maWxlX2ltYWdl/LzE2OTQ4LzY2Mzli/YjcwLWEwMjQtNDZl/NS05NGE0LTM1NjVl/ODRjOTg2OC5qcGc", "badge_ids": [], "article_count": 1}