{"type_of": "user", "id": 543933, "username": "robsonmuniz16", "name": "Robson Muniz", "twitter_username": "WebDevMadeEasy", "github_username": null, "summary": "Hello Dev! \ud83d\udc4b I'm Robson Muniz. I love teaching / coding and learning on YouTube and Facebook.", "location": "", "website_url": "http://www.youtube.com/c/WebDevelopment", "joined_at": "Dec 20, 2020", "profile_image": "https://res.cloudinary.com/practicaldev/image/fetch/s--CFWpjGcB--/c_fill,f_auto,fl_progressive,h_320,q_auto,w_320/https://dev-to-uploads.s3.amazonaws.com/uploads/user/profile_image/543933/9122ae1f-cfb6-4e32-aa8b-ef410f020a0c.png", "article_count": 50}