{"type_of": "user", "id": 592069, "username": "ruchernchong", "name": "Ru Chern Chong", "twitter_username": "ruchern_chong", "github_username": "ruchern-chong", "summary": "", "location": "Singapore", "website_url": "https://ruchern.xyz", "joined_at": "Mar  7, 2021", "profile_image": "https://res.cloudinary.com/practicaldev/image/fetch/s--O3Z4DtZY--/c_fill,f_auto,fl_progressive,h_320,q_auto,w_320/https://dev-to-uploads.s3.amazonaws.com/uploads/user/profile_image/592069/704ceb73-bb04-425f-ab5c-6998ec518c15.JPG", "article_count": 3}