{"type_of": "user", "id": 597098, "username": "viniciusquare", "name": "Vin\u00edcius Quadrado", "twitter_username": null, "github_username": "viniciuSquare", "summary": "\ud83d\udca1Developing the developer inside me\nBrazilian, 22 y, studying mostly ReactJS, Angular, NodeJS & Laravel.", "location": "Paran\u00e1, Brazil", "website_url": "", "joined_at": "Mar 16, 2021", "profile_image": "https://res.cloudinary.com/practicaldev/image/fetch/s--r1hm7CzL--/c_fill,f_auto,fl_progressive,h_320,q_auto,w_320/https://dev-to-uploads.s3.amazonaws.com/uploads/user/profile_image/597098/9df23160-3a10-4a5a-b4be-4ce296c4585f.png", "article_count": 2}