{"type_of": "user", "id": 606615, "username": "dorf8839", "name": "Cory Dorfner", "twitter_username": "cdorfner", "github_username": "dorf8839", "summary": "Avid Learner | Analytical Mindset | Relationship Builder | Achiever | Inspired by the future and what could be.", "location": "", "website_url": "https://corydorfner.com", "joined_at": "Mar 31, 2021", "profile_image": "https://res.cloudinary.com/practicaldev/image/fetch/s--0rKbotO5--/c_fill,f_auto,fl_progressive,h_320,q_auto,w_320/https://dev-to-uploads.s3.amazonaws.com/uploads/user/profile_image/606615/508e6b34-9dbe-4812-b3ef-cdf78aa3bbb7.jpg", "article_count": 24}