{"type_of": "user", "id": 627944, "username": "gusrylmubarok", "name": "gusrylmubarok", "twitter_username": "gusrylmubarok", "github_username": "gusrylmubarok", "summary": "Suka makan nasi | 2 Monitor, 2 Smartphone, 1 Keyboard", "location": "Bandung, Indonesia", "website_url": "", "joined_at": "May  8, 2021", "profile_image": "https://res.cloudinary.com/practicaldev/image/fetch/s--X3uqjDyl--/c_fill,f_auto,fl_progressive,h_320,q_auto,w_320/https://dev-to-uploads.s3.amazonaws.com/uploads/user/profile_image/627944/1289fde0-6445-454c-a90a-bc151f0438d2.jpg", "article_count": 1}