{"type_of": "user", "id": 87103, "username": "kalaspuffar", "name": "Daniel Persson", "twitter_username": "kalaspuffar", "github_username": "kalaspuffar", "summary": "", "location": "Sweden", "website_url": "https://danielpersson.dev", "joined_at": "Jul 25, 2018", "profile_image": "https://res.cloudinary.com/practicaldev/image/fetch/s--6hb2eixn--/c_fill,f_auto,fl_progressive,h_320,q_auto,w_320/https://dev-to-uploads.s3.amazonaws.com/uploads/user/profile_image/87103/587ce00b-a264-49ab-a393-32a40dd339e3.png", "article_count": 50}