{"type_of": "user", "id": 964217, "username": "kheersagar", "name": "kheersagar parja", "twitter_username": "KheersagarParj2", "github_username": "kheersagar", "summary": "I am Full Stack Developer working at Siemens. I have experience in full-stack development for web and mobile applications.", "location": "Raigarh, Chhattisgarh", "website_url": "https://github.com/kheersagar", "joined_at": "Nov  3, 2022", "profile_image": "https://res.cloudinary.com/practicaldev/image/fetch/s--xM3YWTQX--/c_fill,f_auto,fl_progressive,h_320,q_auto,w_320/https://dev-to-uploads.s3.amazonaws.com/uploads/user/profile_image/964217/7f2e7ad7-8751-42c0-b46f-86299bdbf6eb.jpeg", "article_count": 6}