{"type_of": "user", "id": 969958, "username": "webprerender123", "name": "webprerender123", "twitter_username": null, "github_username": "webprerender123", "summary": "Web Prerender helps you in increasing the website rating without decreasing the user experience by showing a static HTML version of your javascript website to web crawler. This platform helps to prere", "location": "Ahmedabad ", "website_url": "https://webprerender.io/", "joined_at": "Nov 10, 2022", "profile_image": "https://res.cloudinary.com/practicaldev/image/fetch/s--vHX0pGIY--/c_fill,f_auto,fl_progressive,h_320,q_auto,w_320/https://dev-to-uploads.s3.amazonaws.com/uploads/user/profile_image/969958/e395b8c6-26a6-4029-8904-aeee2448eaff.png", "article_count": 2}